{
  "address": "Jl. Cerme No.24, Wanasari, Sidanegara, Cilacap, Jawa Tengah 53223",
  "phone": "088905905905",
  "whatsapp": "6288905905905",
  "email": "pmb.unaic@universitasalirsyad.ac.id",
  "operationalHours": "Senin - Jumat, 08.00 - 16.00 WIB",
  "operationalHoursEn": "Monday - Friday, 08:00 AM - 04:00 PM WIB",
  "mapsUrl": "https://www.google.com/maps/embed?pb=!1m18!1m12!1m3!1d3958.1234567890123!2d109.0123456789!3d-7.716123456789012!2m3!1f0!2f0!3f0!3m2!1i1024!2i768!4f13.1!3m3!1m2!1s0x2e655f1234567890%3A0x123456789abcdef!2sUniversitas%20Al-Irsyad%20Cilacap!5e0!3m2!1sen!2sid!4v1234567890123!5m2!1sen!2sid",
  "socialMedia": [
    {
      "name": "Facebook",
      "url": "https://www.facebook.com/universitas.alirsyad.7"
    },
    {
      "name": "Instagram",
      "url": "https://instagram.com/unaicofficial"
    },
    {
      "name": "YouTube",
      "url": "https://www.youtube.com/@unaicofficial"
    },
    {
      "name": "LinkedIn",
      "url": "https://linktr.ee/unaicofficial"
    }
  ],
  "departments": [
    {
      "id": "dept1",
      "name": "Bagian Akademik",
      "nameEn": "Academic Department",
      "description": "Informasi penerimaan mahasiswa baru, kurikulum, dan administrasi akademik",
      "descriptionEn": "Information on new student admissions, curriculum, and academic administration",
      "email": "akademik@unaic.ac.id",
      "phone": "+62 282 123458",
      "head": "Dr. Ahmad Santoso, M.Pd."
    },
    {
      "id": "dept2",
      "name": "Bagian Kemahasiswaan",
      "nameEn": "Student Affairs",
      "description": "Layanan beasiswa, kegiatan mahasiswa, dan pengembangan karir",
      "descriptionEn": "Scholarship services, student activities, and career development",
      "email": "kemahasiswaan@unaic.ac.id",
      "phone": "+62 282 123459",
      "head": "Siti Nurhaliza, S.Pd., M.Si."
    },
    {
      "id": "dept3",
      "name": "Bagian Administrasi",
      "nameEn": "Administration Department",
      "description": "Administrasi umum, keuangan, dan sumber daya manusia",
      "descriptionEn": "General administration, finance, and human resources",
      "email": "administrasi@unaic.ac.id",
      "phone": "+62 282 123460",
      "head": "Budi Setiawan, S.E., M.M."
    },
    {
      "id": "dept4",
      "name": "Bagian Hubungan Masyarakat",
      "nameEn": "Public Relations",
      "description": "Kerjasama, publikasi, dan informasi umum universitas",
      "descriptionEn": "Cooperation, publication, and general university information",
      "email": "humas@unaic.ac.id",
      "phone": "+62 282 123461",
      "head": "Maria Christina, S.I.Kom."
    }
  ]
}